zarr_download.py
zarrofflinedownloader-2025.5.dist-info/licenses/LICENSE
zarrofflinedownloader-2025.5.dist-info/METADATA
zarrofflinedownloader-2025.5.dist-info/WHEEL
zarrofflinedownloader-2025.5.dist-info/entry_points.txt
zarrofflinedownloader-2025.5.dist-info/top_level.txt
zarrofflinedownloader-2025.5.dist-info/RECORD
