Metadata-Version: 2.4
Name: zarrofflinedownloader
Version: 2025.5
Summary: offline zarr downloader
Author-email: Michael Blaschek <michael.blaschek@univie.ac.at>, Emma Haslwanter <emma.haslwanter@univie.ac.at>
Maintainer-email: Emma Haslwanter <emma.haslwanter@univie.ac.at>
License: MIT
Project-URL: Repository, https://gitlab.phaidra.org/imgw/zarr-downloader.git
Project-URL: Issues, https://gitlab.phaidra.org/imgw/zarr-downloader/-/issues
Keywords: zarr,netcdf,download
License-File: LICENSE
Requires-Dist: requests
Requires-Dist: fsspec
Requires-Dist: aiohttp
Requires-Dist: zarr<3.0.0,>2.16.0
Requires-Dist: numpy<2.0.0
Requires-Dist: numcodecs<0.16.0
Requires-Dist: tqdm
Requires-Dist: argparse
Dynamic: license-file
